{
  "artifacts": [],
  "command": "my_main",
  "experiment": {
    "base_dir": "/home/shuqingshi/Downloads/epymarl_ind/src",
    "dependencies": [
      "numpy==2.0.1",
      "PyYAML==5.3.1",
      "sacred==0.8.5",
      "torch==2.4.0"
    ],
    "mainfile": "main.py",
    "name": "pymarl",
    "repositories": [
      {
        "commit": "a6dd71064514a78e82fe9484b195b71627ded90b",
        "dirty": false,
        "url": "git@github.com:stevenqing/epymarl_ind.git"
      },
      {
        "commit": "a6dd71064514a78e82fe9484b195b71627ded90b",
        "dirty": false,
        "url": "git@github.com:stevenqing/epymarl_ind.git"
      },
      {
        "commit": "a6dd71064514a78e82fe9484b195b71627ded90b",
        "dirty": false,
        "url": "git@github.com:stevenqing/epymarl_ind.git"
      }
    ],
    "sources": [
      [
        "main.py",
        "_sources/main_b2cc1db06d11795e4f8cf6a3b0165fa1.py"
      ],
      [
        "run.py",
        "_sources/run_42ee2a9a4a379737572668ddf8c14dea.py"
      ],
      [
        "utils/logging.py",
        "_sources/logging_80685d67fab61f6e71e93fbe28085531.py"
      ]
    ]
  },
  "heartbeat": "2024-08-13T18:54:03.592605",
  "host": {
    "ENV": {},
    "cpu": "13th Gen Intel(R) Core(TM) i7-1365U",
    "hostname": "nmslap007078",
    "os": [
      "Linux",
      "Linux-6.5.0-41-generic-x86_64-with-glibc2.35"
    ],
    "python_version": "3.9.0"
  },
  "meta": {
    "command": "my_main",
    "config_updates": {
      "env_args": {
        "key": "lbforaging:Foraging-8x8-3p-3f-v3",
        "time_limit": 25
      }
    },
    "named_configs": [],
    "options": {
      "--beat-interval": null,
      "--capture": null,
      "--comment": null,
      "--debug": false,
      "--enforce_clean": false,
      "--file_storage": null,
      "--force": false,
      "--help": false,
      "--id": null,
      "--loglevel": null,
      "--mongo_db": null,
      "--name": null,
      "--pdb": false,
      "--print-config": false,
      "--priority": null,
      "--queue": false,
      "--s3": null,
      "--sql": null,
      "--tiny_db": null,
      "--unobserved": false,
      "COMMAND": null,
      "UPDATE": [
        "env_args.time_limit=25",
        "env_args.key=lbforaging:Foraging-8x8-3p-3f-v3"
      ],
      "help": false,
      "with": true
    }
  },
  "resources": [],
  "result": null,
  "start_time": "2024-08-13T18:51:23.390672",
  "status": "RUNNING"
}